celeryanalytics/__init__.py
celeryanalytics/admin.py
celeryanalytics/api.py
celeryanalytics/app_settings.py
celeryanalytics/apps.py
celeryanalytics/auth_hooks.py
celeryanalytics/models.py
celeryanalytics/signals.py
celeryanalytics/tasks.py
celeryanalytics/urls.py
celeryanalytics/views.py
celeryanalytics/locale/de/LC_MESSAGES/django.po
celeryanalytics/locale/en/LC_MESSAGES/django.mo
celeryanalytics/locale/en/LC_MESSAGES/django.po
celeryanalytics/management/__init__.py
celeryanalytics/management/commands/__init__.py
celeryanalytics/management/commands/ca_run_housekeeping.py
celeryanalytics/management/commands/ca_setup_task.py
celeryanalytics/migrations/0001_initial.py
celeryanalytics/migrations/0002_auto_20200407_1433.py
celeryanalytics/migrations/0003_auto_20210314_0151.py
celeryanalytics/migrations/0004_alter_celerytaskcompleted_task_and_more.py
celeryanalytics/migrations/__init__.py
celeryanalytics/static/__init__.py
celeryanalytics/static/celeryanalytics/__init__.py
celeryanalytics/static/celeryanalytics/static/css/main.881b38e4.css
celeryanalytics/static/celeryanalytics/static/css/main.881b38e4.css.map
celeryanalytics/static/celeryanalytics/static/js/main.b931496b.js
celeryanalytics/static/celeryanalytics/static/js/main.b931496b.js.LICENSE.txt
celeryanalytics/static/celeryanalytics/static/js/main.b931496b.js.map
celeryanalytics/templates/__init__.py
celeryanalytics/templates/celeryanalytics/__init__.py
celeryanalytics/templates/celeryanalytics/react_base.html
allianceauth_celeryanalytics-0.0.7.dist-info/licenses/LICENSE
allianceauth_celeryanalytics-0.0.7.dist-info/WHEEL
allianceauth_celeryanalytics-0.0.7.dist-info/METADATA
allianceauth_celeryanalytics-0.0.7.dist-info/RECORD
